Metadata-Version: 2.1
Name: qobuz-dl
Version: 0.9.9.10
Summary: The complete Lossless and Hi-Res music downloader for Qobuz
Home-page: https://github.com/vitiko98/Qobuz-DL
Author: Vitiko
Author-email: vhnz98@gmail.com
Classifier: Programming Language :: Python :: 3
Classifier: License :: OSI Approved :: GNU General Public License (GPL)
Classifier: Operating System :: OS Independent
Requires-Python: >=3.6
License-File: LICENSE
